{
  "cash_usd": 10000.0,
  "equity_curve": [
    {
      "at": "2026-04-23T14:19:18.992329+00:00",
      "equity": 10000.0,
      "source": "shadow_challenger"
    },
    {
      "at": "2026-04-23T14:20:26.058579+00:00",
      "equity": 10000.0,
      "source": "shadow_challenger"
    },
    {
      "at": "2026-04-23T14:21:33.436659+00:00",
      "equity": 10000.0,
      "source": "shadow_challenger"
    },
    {
      "at": "2026-04-23T14:22:40.550103+00:00",
      "equity": 10000.0,
      "source": "shadow_challenger"
    },
    {
      "at": "2026-04-23T14:23:47.627050+00:00",
      "equity": 10000.0,
      "source": "shadow_challenger"
    },
    {
      "at": "2026-04-23T14:24:54.638022+00:00",
      "equity": 10000.0,
      "source": "shadow_challenger"
    },
    {
      "at": "2026-04-23T14:26:01.654437+00:00",
      "equity": 10000.0,
      "source": "shadow_challenger"
    },
    {
      "at": "2026-04-23T14:27:08.713189+00:00",
      "equity": 10000.0,
      "source": "shadow_challenger"
    },
    {
      "at": "2026-04-23T14:28:15.926629+00:00",
      "equity": 10000.0,
      "source": "shadow_challenger"
    },
    {
      "at": "2026-04-23T14:29:22.805017+00:00",
      "equity": 10000.0,
      "source": "shadow_challenger"
    }
  ],
  "initial_cash_usd": 10000.0,
  "positions": {},
  "realized_pnl": 0.0,
  "trade_history": []
}